cplay.py
cplay_ng-5.4.0.dist-info/AUTHORS
cplay_ng-5.4.0.dist-info/LICENSE
cplay_ng-5.4.0.dist-info/METADATA
cplay_ng-5.4.0.dist-info/WHEEL
cplay_ng-5.4.0.dist-info/entry_points.txt
cplay_ng-5.4.0.dist-info/top_level.txt
cplay_ng-5.4.0.dist-info/RECORD
