Metadata-Version: 2.1
Name: cplay-ng
Version: 5.4.0
Summary: A simple curses audio player
Author-email: Ulf Betlehem <flu@iki.fi>
Maintainer-email: Tobias Bengfort <tobias.bengfort@posteo.de>
License: GPLv2+
Project-URL: Homepage, https://github.com/xi/cplay-ng
Keywords: music-player,curses
Classifier: Development Status :: 5 - Production/Stable
Classifier: Environment :: Console :: Curses
Classifier: Intended Audience :: End Users/Desktop
Classifier: Natural Language :: English
Classifier: Operating System :: OS Independent
Classifier: Programming Language :: Python
License-File: LICENSE
License-File: AUTHORS
